data/__init__.py
data/single_list.py
kitch.data-0.0.1.dist-info/DESCRIPTION.rst
kitch.data-0.0.1.dist-info/METADATA
kitch.data-0.0.1.dist-info/RECORD
kitch.data-0.0.1.dist-info/WHEEL
kitch.data-0.0.1.dist-info/metadata.json
kitch.data-0.0.1.dist-info/top_level.txt
