Metadata-Version: 2.0
Name: kitch.data
Version: 0.0.1
Summary: A collection of data structures
Home-page: https://github.com/j-kitch/data
Author: Joshua Kitchen
Author-email: joshdkitchen@gmail.com
License: UNKNOWN
Keywords: data structures education linked list
Platform: UNKNOWN
Classifier: Development Status :: 1 - Planning
Classifier: Environment :: Console
Classifier: Intended Audience :: Other Audience
Classifier: License :: OSI Approved :: MIT License
Classifier: Natural Language :: English
Classifier: Operating System :: POSIX :: Linux
Classifier: Programming Language :: Python :: 3.5
Classifier: Programming Language :: Python :: Implementation :: CPython
Classifier: Topic :: Software Development :: Libraries :: Python Modules
